sunpy_regards/__init__.py
sunpy_regards/config.py
sunpy_regards/adapters/__init__.py
sunpy_regards/adapters/sunpy/__init__.py
sunpy_regards/adapters/sunpy/_attrs.py
sunpy_regards/adapters/sunpy/attrs.py
sunpy_regards/adapters/sunpy/client.py
sunpy_regards/application/__init__.py
sunpy_regards/application/dto.py
sunpy_regards/application/ports.py
sunpy_regards/application/use_cases.py
sunpy_regards/domain/__init__.py
sunpy_regards/domain/entities.py
sunpy_regards/domain/exceptions.py
sunpy_regards/domain/value_objects.py
sunpy_regards/infrastructure/__init__.py
sunpy_regards/infrastructure/http/__init__.py
sunpy_regards/infrastructure/http/auth.py
sunpy_regards/infrastructure/http/regards_client.py
sunpy_regards/infrastructure/mappers/__init__.py
sunpy_regards/infrastructure/mappers/regards_mapper.py
sunpy_regards-1.0.0.dist-info/METADATA
sunpy_regards-1.0.0.dist-info/WHEEL
sunpy_regards-1.0.0.dist-info/entry_points.txt
sunpy_regards-1.0.0.dist-info/top_level.txt
sunpy_regards-1.0.0.dist-info/RECORD
