Metadata-Version: 2.4
Name: sunpy-regards
Version: 1.0.0
Summary: SunPy Fido client for the REGARDS archive at MEDOC.
Author-email: Salim Hachemaoui <salim.hachemaoui@group-dsi.com>
License-Expression: BSD-3-Clause
Project-URL: Homepage, https://git.ias.u-psud.fr/medoc/sunpy-regards
Project-URL: Source, https://git.ias.u-psud.fr/medoc/sunpy-regards
Project-URL: Issues, https://git.ias.u-psud.fr/medoc/sunpy-regards/-/issues
Keywords: sunpy,astronomy,solar,regards,medoc,fido
Classifier: Development Status :: 3 - Alpha
Classifier: Intended Audience :: Science/Research
Classifier: Programming Language :: Python :: 3
Classifier: Programming Language :: Python :: 3.11
Classifier: Programming Language :: Python :: 3.12
Classifier: Topic :: Scientific/Engineering :: Astronomy
Requires-Python: >=3.11
Requires-Dist: sunpy[all]>=7.0
Requires-Dist: astropy>=5.0
Requires-Dist: requests>=2.31
Requires-Dist: python-dotenv>=1.0
Provides-Extra: dev
Requires-Dist: pytest; extra == "dev"
Requires-Dist: pytest-cov; extra == "dev"
Requires-Dist: ruff; extra == "dev"
Requires-Dist: black; extra == "dev"
Requires-Dist: mypy; extra == "dev"
Requires-Dist: build; extra == "dev"
Requires-Dist: python-semantic-release; extra == "dev"
